{
  "fields": [
    {
      "key": "gender",
      "name": "Gender",
      "type": "text"
    },
    {
      "key": "age",
      "name": "Age",
      "type": "number"
    },
    {
      "key": "join_date",
      "name": "Join Date",
      "type": "datetime"
    }
  ],
  "groups": [
    {
      "uuid": "11f83067-7c40-49e8-8a35-a1a4e8dd3b69",
      "name": "Testers",
      "query": ""
    },
    {
      "uuid": "372aba66-16e2-44ee-8486-fb5cedfe51d9",
      "name": "Customers",
      "query": ""
    },
    {
      "uuid": "63867d07-c033-4ef1-957c-85fa9708c19c",
      "name": "Youth",
      "query": "age <= 18"
    }
  ],
  "flows": [
    {
      "uuid": "ed8cf8d4-a42c-4ce1-a7e3-44a2918e3cec",
      "name": "Contact Details",
      "spec_version": "12.0",
      "language": "base",
      "type": "messaging_offline",
      "revision": 20,
      "expire_after_minutes": 10080,
      "localization": {},
      "nodes": [
        {
          "uuid": "c50f7200-2432-4912-897d-d809a2d2ad8d",
          "actions": [
            {
              "type": "send_msg",
              "uuid": "67aafaf6-b375-461c-8357-fd760423f96c",
              "text": "Hi there. What's your name?"
            }
          ],
          "exits": [
            {
              "uuid": "cd1cba4d-ddb6-4491-8f53-19647e193f25",
              "destination_node_uuid": "dcd9295d-7a25-4a77-abc2-7d692ca6cc1f"
            }
          ]
        },
        {
          "uuid": "dc72d0fd-c918-44e9-a833-31a58f066df5",
          "actions": [
            {
              "type": "set_contact_name",
              "uuid": "fac97ece-b9ab-4480-a6dd-9968cb5ebe79",
              "name": "@results.name"
            },
            {
              "type": "send_msg",
              "uuid": "a5141d43-14a1-4e40-914c-f2b33b3645de",
              "text": "Thanks @contact.name. What's your phone number?"
            }
          ],
          "exits": [
            {
              "uuid": "3c09be15-46a0-4e29-bdbd-e512bf454012",
              "destination_node_uuid": "260710c6-f7eb-4dfb-a297-9736b65e7a95"
            }
          ]
        },
        {
          "uuid": "b09ed9b4-0d44-4096-bc2d-263e9e3dec93",
          "actions": [
            {
              "type": "add_contact_urn",
              "uuid": "a3bea28b-b1b0-4db1-af75-090973f9eb63",
              "scheme": "tel",
              "path": "@results.phone"
            },
            {
              "type": "add_contact_groups",
              "uuid": "5126bb19-6ca1-4a9c-a9ef-30f4dd3761f4",
              "groups": [
                {
                  "uuid": "11f83067-7c40-49e8-8a35-a1a4e8dd3b69",
                  "name": "Testers"
                }
              ]
            }
          ],
          "exits": [
            {
              "uuid": "242eb71a-704a-4de5-bbff-e2bcca10d888"
            }
          ]
        },
        {
          "uuid": "76a47c79-bae6-46f7-a43e-89fb67191a7b",
          "actions": [
            {
              "type": "send_msg",
              "uuid": "bde2299b-7f35-4ad9-98c3-7e8db18c34ac",
              "text": "Sorry that doesn't look like a phone number. Try again."
            }
          ],
          "exits": [
            {
              "uuid": "aa6517e2-c06c-49c1-8a6a-acea0a474ecb",
              "destination_node_uuid": "260710c6-f7eb-4dfb-a297-9736b65e7a95"
            }
          ]
        },
        {
          "uuid": "dcd9295d-7a25-4a77-abc2-7d692ca6cc1f",
          "wait": {
            "type": "msg"
          },
          "router": {
            "type": "switch",
            "result_name": "Name",
            "default_exit_uuid": "acd7c0cc-bf92-458e-a03c-d563f397e70c",
            "operand": "@input",
            "cases": []
          },
          "exits": [
            {
              "uuid": "acd7c0cc-bf92-458e-a03c-d563f397e70c",
              "destination_node_uuid": "dc72d0fd-c918-44e9-a833-31a58f066df5",
              "name": "All Responses"
            }
          ]
        },
        {
          "uuid": "260710c6-f7eb-4dfb-a297-9736b65e7a95",
          "wait": {
            "type": "msg"
          },
          "router": {
            "type": "switch",
            "result_name": "Phone",
            "default_exit_uuid": "ca4748f3-439a-49f6-a3b7-5868653fceb4",
            "operand": "@input",
            "cases": [
              {
                "uuid": "4cf95d5c-a29a-4ddf-81b6-dede56f506ab",
                "type": "has_phone",
                "exit_uuid": "eb2138cb-90a9-4824-ad92-147d59aaa71a"
              }
            ]
          },
          "exits": [
            {
              "uuid": "eb2138cb-90a9-4824-ad92-147d59aaa71a",
              "destination_node_uuid": "b09ed9b4-0d44-4096-bc2d-263e9e3dec93",
              "name": "phone"
            },
            {
              "uuid": "ca4748f3-439a-49f6-a3b7-5868653fceb4",
              "destination_node_uuid": "76a47c79-bae6-46f7-a43e-89fb67191a7b",
              "name": "Other"
            }
          ]
        }
      ]
    },
    {
      "uuid": "bdd61538-5f50-4836-a8fb-acaafd64ddb1",
      "name": "Two Questions",
      "spec_version": "12.0",
      "language": "base",
      "type": "messaging_offline",
      "revision": 24,
      "expire_after_minutes": 10080,
      "localization": {},
      "nodes": [
        {
          "uuid": "6f26e808-c1a2-4e52-b6f3-4d2dd79ffb24",
          "actions": [
            {
              "type": "send_msg",
              "uuid": "450d2c77-a2d2-4cec-8a97-a96c5d7bf126",
              "text": "What is your favorite beer?"
            }
          ],
          "exits": [
            {
              "uuid": "bf56b8cc-3801-4a15-a307-73d277694896",
              "destination_node_uuid": "e1dbee2c-17df-471d-9768-eec94a3343c0"
            }
          ]
        },
        {
          "uuid": "b12ed7f7-2d2c-4c59-8c2e-2cccee06ce57",
          "actions": [
            {
              "type": "send_msg",
              "uuid": "4c3be4d2-c994-4e28-946c-5ea9ee33659a",
              "text": "@results.beer.category_localized is a great beer! What is your favorite color?"
            }
          ],
          "exits": [
            {
              "uuid": "99ac70fb-2d81-4d24-94a3-d031123e137b",
              "destination_node_uuid": "7854b048-038c-44fe-88c5-f62fd599b556"
            }
          ]
        },
        {
          "uuid": "6980dc8d-7787-4a83-a603-5b84fd8e87f9",
          "actions": [
            {
              "type": "send_msg",
              "uuid": "5e5b8b5a-b638-4a58-94a6-bb79814f4712",
              "text": "I didn't recognize that beer. Please try again."
            }
          ],
          "exits": [
            {
              "uuid": "9257e3e9-ff08-4707-ad86-398e8e34bb7c",
              "destination_node_uuid": "e1dbee2c-17df-471d-9768-eec94a3343c0"
            }
          ]
        },
        {
          "uuid": "f4bb2acf-7ba0-448f-93ff-c4192b95169a",
          "actions": [
            {
              "type": "send_msg",
              "uuid": "a3ad6679-a32c-4af0-babc-2def65adc185",
              "text": "Ok let's go get some @results.color.category_localized @results.beer.category_localized!"
            }
          ],
          "exits": [
            {
              "uuid": "7b4ede52-3fa2-451c-955e-f5b0cb4c7030"
            }
          ]
        },
        {
          "uuid": "504f5813-b500-431f-b7db-244606c9696b",
          "actions": [
            {
              "type": "send_msg",
              "uuid": "5ed80e3b-d6ec-4b25-bbbf-39ae8935ab00",
              "text": "@results.color.input isn't a color I know. Please try again."
            }
          ],
          "exits": [
            {
              "uuid": "91e8b04d-8412-419e-9062-1877a23e377a",
              "destination_node_uuid": "7854b048-038c-44fe-88c5-f62fd599b556"
            }
          ]
        },
        {
          "uuid": "e1dbee2c-17df-471d-9768-eec94a3343c0",
          "wait": {
            "type": "msg"
          },
          "router": {
            "type": "switch",
            "result_name": "Beer",
            "default_exit_uuid": "c0d4fdd1-ec6c-4b6d-927d-c7f532989274",
            "operand": "@input",
            "cases": [
              {
                "uuid": "b7a531c0-6cda-4163-906f-b61eaa1fb12c",
                "type": "has_any_word",
                "arguments": [
                  "Club"
                ],
                "exit_uuid": "9f484724-9adb-40da-9da3-d99973591e27"
              },
              {
                "uuid": "a8d6f1ab-b84f-4ea0-8fc4-27b2a9283e86",
                "type": "has_any_word",
                "arguments": [
                  "Pilsner"
                ],
                "exit_uuid": "7993051a-a2d9-4387-9cdb-bd0f48c288a3"
              },
              {
                "uuid": "501ae89b-1a31-472f-a1ef-7dd583630202",
                "type": "has_any_word",
                "arguments": [
                  "Mutzig"
                ],
                "exit_uuid": "447b17a3-9f22-4267-b9bc-754036f842ce"
              }
            ]
          },
          "exits": [
            {
              "uuid": "9f484724-9adb-40da-9da3-d99973591e27",
              "destination_node_uuid": "b12ed7f7-2d2c-4c59-8c2e-2cccee06ce57",
              "name": "Club"
            },
            {
              "uuid": "7993051a-a2d9-4387-9cdb-bd0f48c288a3",
              "destination_node_uuid": "b12ed7f7-2d2c-4c59-8c2e-2cccee06ce57",
              "name": "Pilsner"
            },
            {
              "uuid": "447b17a3-9f22-4267-b9bc-754036f842ce",
              "destination_node_uuid": "b12ed7f7-2d2c-4c59-8c2e-2cccee06ce57",
              "name": "Mutzig"
            },
            {
              "uuid": "c0d4fdd1-ec6c-4b6d-927d-c7f532989274",
              "destination_node_uuid": "6980dc8d-7787-4a83-a603-5b84fd8e87f9",
              "name": "Other"
            }
          ]
        },
        {
          "uuid": "7854b048-038c-44fe-88c5-f62fd599b556",
          "wait": {
            "type": "msg"
          },
          "router": {
            "type": "switch",
            "result_name": "Color",
            "default_exit_uuid": "a45d84cc-725b-4626-98fd-54c64eff0e20",
            "operand": "@input",
            "cases": [
              {
                "uuid": "b8da3fdd-1209-4666-b409-dadac67fc2a7",
                "type": "has_any_word",
                "arguments": [
                  "red"
                ],
                "exit_uuid": "46f73b0a-5845-4392-b5bf-f74c07bb1217"
              },
              {
                "uuid": "912171a6-0afd-469b-8653-80fb50d9d1dc",
                "type": "has_any_word",
                "arguments": [
                  "blue"
                ],
                "exit_uuid": "26d3ec68-245c-49d9-b33f-35d590041827"
              },
              {
                "uuid": "df03e346-102b-4962-9629-b127cdf0dffe",
                "type": "has_any_word",
                "arguments": [
                  "green"
                ],
                "exit_uuid": "646d954d-9e6e-4e38-9a78-0df08b38b7ac"
              }
            ]
          },
          "exits": [
            {
              "uuid": "46f73b0a-5845-4392-b5bf-f74c07bb1217",
              "destination_node_uuid": "f4bb2acf-7ba0-448f-93ff-c4192b95169a",
              "name": "Red"
            },
            {
              "uuid": "26d3ec68-245c-49d9-b33f-35d590041827",
              "destination_node_uuid": "f4bb2acf-7ba0-448f-93ff-c4192b95169a",
              "name": "Blue"
            },
            {
              "uuid": "646d954d-9e6e-4e38-9a78-0df08b38b7ac",
              "destination_node_uuid": "f4bb2acf-7ba0-448f-93ff-c4192b95169a",
              "name": "Green"
            },
            {
              "uuid": "a45d84cc-725b-4626-98fd-54c64eff0e20",
              "destination_node_uuid": "504f5813-b500-431f-b7db-244606c9696b",
              "name": "Other"
            }
          ]
        }
      ]
    },
    {
      "uuid": "e54809ba-2f28-439b-b90b-c623eafa05ae",
      "name": "Multimedia",
      "spec_version": "12.0",
      "language": "base",
      "type": "messaging_offline",
      "revision": 24,
      "expire_after_minutes": 10080,
      "localization": {},
      "nodes": [
        {
          "uuid": "3d02c74d-e5c2-4590-b679-03f988592013",
          "actions": [
            {
              "type": "send_msg",
              "uuid": "58f8384d-92b3-41d2-804f-8c4c6240924e",
              "text": "Hi there, please send a selfie"
            }
          ],
          "exits": [
            {
              "uuid": "d7de8701-2c58-4108-89a9-ec74e9ea619b",
              "destination_node_uuid": "6ab79191-da91-4096-a589-6f3c7f5ecf0c"
            }
          ]
        },
        {
          "uuid": "8befaab2-63cb-4fdc-b44b-62d4a00a40e9",
          "actions": [
            {
              "type": "send_msg",
              "uuid": "dce3e627-65f5-4396-b5d3-67ed6f0b95ef",
              "text": "Now send a video"
            }
          ],
          "exits": [
            {
              "uuid": "7ec846f0-a0f1-48c5-bf8f-5f941558c673",
              "destination_node_uuid": "f5ba9174-ed8c-41cd-898a-d7449f72b916"
            }
          ]
        },
        {
          "uuid": "8de09049-f474-4fed-a079-b0e559a8ac59",
          "actions": [
            {
              "type": "send_msg",
              "uuid": "6c21c268-759e-4156-b074-e4a3fed0dda3",
              "text": "Now send an audio recording"
            }
          ],
          "exits": [
            {
              "uuid": "1b3972b7-e926-46c5-ae30-017038be36c4",
              "destination_node_uuid": "1250d717-bcef-45ed-b63e-e2e8eae953b1"
            }
          ]
        },
        {
          "uuid": "68829693-c442-4c16-9b77-ed384fd607b5",
          "actions": [
            {
              "type": "send_msg",
              "uuid": "f210c97b-9020-43d6-99e2-631e2e62e97b",
              "text": "Finally please send your location"
            }
          ],
          "exits": [
            {
              "uuid": "ad0699ae-d489-4a63-96eb-716c42669321",
              "destination_node_uuid": "78d1b543-e774-4040-b6dc-53139b5edb60"
            }
          ]
        },
        {
          "uuid": "a2d7e973-4499-48d2-852a-cf46f6c69405",
          "actions": [
            {
              "type": "send_msg",
              "uuid": "1f30ac69-69d6-41bb-8e53-56d380704e37",
              "text": "Thanks!"
            }
          ],
          "exits": [
            {
              "uuid": "68ab09e3-3522-4411-87af-f444e00f033d"
            }
          ]
        },
        {
          "uuid": "6ab79191-da91-4096-a589-6f3c7f5ecf0c",
          "wait": {
            "type": "msg",
            "media_hint": "image"
          },
          "router": {
            "type": "switch",
            "result_name": "Selfie",
            "default_exit_uuid": "5736d5b0-8ded-4755-a6a3-83bf593af87d",
            "operand": "@input",
            "cases": []
          },
          "exits": [
            {
              "uuid": "5736d5b0-8ded-4755-a6a3-83bf593af87d",
              "destination_node_uuid": "8befaab2-63cb-4fdc-b44b-62d4a00a40e9",
              "name": "All Responses"
            }
          ]
        },
        {
          "uuid": "f5ba9174-ed8c-41cd-898a-d7449f72b916",
          "wait": {
            "type": "msg",
            "media_hint": "video"
          },
          "router": {
            "type": "switch",
            "result_name": "Vlog",
            "default_exit_uuid": "79ab9eb5-1d5d-4c8b-9e7d-7b02f624fa23",
            "operand": "@input",
            "cases": []
          },
          "exits": [
            {
              "uuid": "79ab9eb5-1d5d-4c8b-9e7d-7b02f624fa23",
              "destination_node_uuid": "8de09049-f474-4fed-a079-b0e559a8ac59",
              "name": "All Responses"
            }
          ]
        },
        {
          "uuid": "1250d717-bcef-45ed-b63e-e2e8eae953b1",
          "wait": {
            "type": "msg",
            "media_hint": "audio"
          },
          "router": {
            "type": "switch",
            "result_name": "Recording",
            "default_exit_uuid": "07662cfe-1270-40ee-b593-c93b4e0a2949",
            "operand": "@input",
            "cases": []
          },
          "exits": [
            {
              "uuid": "07662cfe-1270-40ee-b593-c93b4e0a2949",
              "destination_node_uuid": "68829693-c442-4c16-9b77-ed384fd607b5",
              "name": "All Responses"
            }
          ]
        },
        {
          "uuid": "78d1b543-e774-4040-b6dc-53139b5edb60",
          "wait": {
            "type": "msg",
            "media_hint": "gps"
          },
          "router": {
            "type": "switch",
            "result_name": "Location",
            "default_exit_uuid": "88836f88-82f0-405c-a2f7-dac7b950e198",
            "operand": "@input",
            "cases": []
          },
          "exits": [
            {
              "uuid": "88836f88-82f0-405c-a2f7-dac7b950e198",
              "destination_node_uuid": "a2d7e973-4499-48d2-852a-cf46f6c69405",
              "name": "All Responses"
            }
          ]
        }
      ]
    }
  ]
}